jmat
