Metadata-Version: 1.0
Name: jmat
Version: 0.2
Summary: A package to work with matrix operations
Home-page: UNKNOWN
Author: João Schubnell
Author-email: jschubnell@protonmail.com
License: UNKNOWN
Platform: UNKNOWN
